ALittleBookOfPythonForMultivariateAnalysis/README.md
ALittleBookOfPythonForMultivariateAnalysis/__init__.py
ALittleBookOfPythonForMultivariateAnalysis/__main__.py
ALittleBookOfPythonForMultivariateAnalysis/file.epub
ALittleBookOfPythonForMultivariateAnalysis/index.html
ALittleBookOfPythonForMultivariateAnalysis/css/__init__.py
ALittleBookOfPythonForMultivariateAnalysis/css/annotations.css
ALittleBookOfPythonForMultivariateAnalysis/css/main.css
ALittleBookOfPythonForMultivariateAnalysis/css/normalize.css
ALittleBookOfPythonForMultivariateAnalysis/css/popup.css
ALittleBookOfPythonForMultivariateAnalysis/font/__init__.py
ALittleBookOfPythonForMultivariateAnalysis/font/fontello.eot
ALittleBookOfPythonForMultivariateAnalysis/font/fontello.svg
ALittleBookOfPythonForMultivariateAnalysis/font/fontello.ttf
ALittleBookOfPythonForMultivariateAnalysis/font/fontello.woff
ALittleBookOfPythonForMultivariateAnalysis/img/__init__.py
ALittleBookOfPythonForMultivariateAnalysis/img/annotator-glyph-sprite.png
ALittleBookOfPythonForMultivariateAnalysis/img/annotator-icon-sprite.png
ALittleBookOfPythonForMultivariateAnalysis/img/apple-touch-icon.png
ALittleBookOfPythonForMultivariateAnalysis/img/cancelfullscreen.png
ALittleBookOfPythonForMultivariateAnalysis/img/close.png
ALittleBookOfPythonForMultivariateAnalysis/img/fullscreen.png
ALittleBookOfPythonForMultivariateAnalysis/img/loader.gif
ALittleBookOfPythonForMultivariateAnalysis/img/menu-icon.png
ALittleBookOfPythonForMultivariateAnalysis/img/save.png
ALittleBookOfPythonForMultivariateAnalysis/img/saved.png
ALittleBookOfPythonForMultivariateAnalysis/img/settings-s.png
ALittleBookOfPythonForMultivariateAnalysis/img/settings.png
ALittleBookOfPythonForMultivariateAnalysis/img/star.png
ALittleBookOfPythonForMultivariateAnalysis/js/__init__.py
ALittleBookOfPythonForMultivariateAnalysis/js/epub.js
ALittleBookOfPythonForMultivariateAnalysis/js/epub.min.js
ALittleBookOfPythonForMultivariateAnalysis/js/epub.min.map
a_little_book_of_python_for_multivariate_analysis-2024.3.3.0.dist-info/METADATA
a_little_book_of_python_for_multivariate_analysis-2024.3.3.0.dist-info/WHEEL
a_little_book_of_python_for_multivariate_analysis-2024.3.3.0.dist-info/entry_points.txt
a_little_book_of_python_for_multivariate_analysis-2024.3.3.0.dist-info/top_level.txt
a_little_book_of_python_for_multivariate_analysis-2024.3.3.0.dist-info/RECORD
